src/__init__.py
src/dnres_cli.py
dnres_cli-0.20.dist-info/LICENSE
dnres_cli-0.20.dist-info/METADATA
dnres_cli-0.20.dist-info/WHEEL
dnres_cli-0.20.dist-info/entry_points.txt
dnres_cli-0.20.dist-info/top_level.txt
dnres_cli-0.20.dist-info/RECORD
